README
setup.py
src/SpiffWikiMarkup/Cell.py
src/SpiffWikiMarkup/Html2Wiki.py
src/SpiffWikiMarkup/Wiki2Html.py
src/SpiffWikiMarkup/WikiParser.py
src/SpiffWikiMarkup/__init__.py
src/SpiffWikiMarkup.egg-info/PKG-INFO
src/SpiffWikiMarkup.egg-info/SOURCES.txt
src/SpiffWikiMarkup.egg-info/dependency_links.txt
src/SpiffWikiMarkup.egg-info/top_level.txt
src/SpiffWikiMarkup/Plex/Actions.py
src/SpiffWikiMarkup/Plex/DFA.py
src/SpiffWikiMarkup/Plex/Errors.py
src/SpiffWikiMarkup/Plex/Lexicons.py
src/SpiffWikiMarkup/Plex/Machines.py
src/SpiffWikiMarkup/Plex/Regexps.py
src/SpiffWikiMarkup/Plex/Scanners.py
src/SpiffWikiMarkup/Plex/Timing.py
src/SpiffWikiMarkup/Plex/Traditional.py
src/SpiffWikiMarkup/Plex/Transitions.py
src/SpiffWikiMarkup/Plex/__init__.py
src/SpiffWikiMarkup/Plex/test_tm.py