Metadata-Version: 1.0
Name: SpiffWikiMarkup
Version: 0.4.0
Summary: A library for converting between HTML and Wiki text
Home-page: http://code.google.com/p/spiff-wikimarkup/
Author: Samuel Abels
Author-email: cheeseshop.python.org@debain.org
License: GPLv2
Keywords: spiff wikimarkup wiki markup html convert bidirectional
Platform: UNKNOWN
Classifier: Development Status :: 5 - Production/Stable
Classifier: Intended Audience :: Developers
Classifier: License :: OSI Approved :: GNU General Public License (GPL)
Classifier: Programming Language :: Python
Classifier: Topic :: Software Development :: Libraries
Classifier: Topic :: Software Development :: Libraries :: Python Modules
